deo_client/__init__.py
deo_client/client.py
deo_client/py.typed
deo_client/types.py
tests/test_client.py
deo_client-0.0.1.dist-info/METADATA
deo_client-0.0.1.dist-info/WHEEL
deo_client-0.0.1.dist-info/top_level.txt
deo_client-0.0.1.dist-info/RECORD
