Metadata-Version: 2.4
Name: deo-client
Version: 0.0.1
Summary: Python client for the deo document database
Author-email: myferr <contactme.myfer@protonmail.com>
License: MIT
Project-URL: Homepage, https://github.com/myferr/deo
Project-URL: Documentation, https://github.com/myferr/deo#readme
Project-URL: Repository, https://github.com/myferr/deo.git
Project-URL: Issues, https://github.com/myferr/deo/issues
Keywords: database,document,json,msgpack,rest,api
Classifier: Development Status :: 3 - Alpha
Classifier: Intended Audience :: Developers
Classifier: License :: OSI Approved :: MIT License
Classifier: Operating System :: OS Independent
Classifier: Programming Language :: Python :: 3
Classifier: Programming Language :: Python :: 3.8
Classifier: Programming Language :: Python :: 3.9
Classifier: Programming Language :: Python :: 3.10
Classifier: Programming Language :: Python :: 3.11
Classifier: Programming Language :: Python :: 3.12
Classifier: Programming Language :: Python :: 3.13
Classifier: Topic :: Database
Classifier: Topic :: Software Development :: Libraries :: Python Modules
Requires-Python: >=3.8
Requires-Dist: requests>=2.25.0
Provides-Extra: dev
Requires-Dist: pytest>=6.0; extra == "dev"
Requires-Dist: pytest-mock>=3.0; extra == "dev"
Requires-Dist: mypy>=1.0; extra == "dev"
Requires-Dist: ruff>=0.1.0; extra == "dev"
Requires-Dist: types-requests>=2.25.0; extra == "dev"
